README.md
pyproject.toml
setup.py
river_mwclient/__init__.py
river_mwclient/auth_credentials.py
river_mwclient/cargo_client.py
river_mwclient/errors.py
river_mwclient/esports_client.py
river_mwclient/esports_lookup_cache.py
river_mwclient/extended_page.py
river_mwclient/gamepedia_client.py
river_mwclient/namespace.py
river_mwclient/page_modifier.py
river_mwclient/session_manager.py
river_mwclient/site.py
river_mwclient/template_modifier.py
river_mwclient/wiki_client.py
river_mwclient/wiki_content_error.py
river_mwclient/wiki_error.py
river_mwclient/wiki_script_error.py
river_mwclient/wiki_time.py
river_mwclient/wiki_time_parser.py
river_mwclient.egg-info/PKG-INFO
river_mwclient.egg-info/SOURCES.txt
river_mwclient.egg-info/dependency_links.txt
river_mwclient.egg-info/requires.txt
river_mwclient.egg-info/top_level.txt