Metadata-Version: 2.1
Name: river-mwclient
Version: 0.3.2
Summary: River's mwclient wrapper
Home-page: https://github.com/RheingoldRiver/river_mwclient
Author: RheingoldRiver
Author-email: river.esports@gmail.com
License: UNKNOWN
Platform: UNKNOWN
Requires-Python: >=3.6
